RmPDFWaterMark
