Metadata-Version: 2.1
Name: RmPDFWaterMark
Version: 0.1.1
Summary: 若干pdf水印处理
Home-page: UNKNOWN
Author: xcc
Author-email: xinchacha@xcc.com
License: UNKNOWN
Platform: UNKNOWN
